docs/CONTRIBUTING.md
docs/_config.yml
docs/_toc.yml
docs/api.md
docs/build_book.sh
docs/intro.md
docs/splash_image.png
docs/control/control_overview.md
docs/control/open-loop_controllers.md
docs/control/pyomo_controllers.md
docs/control/figures/flex_demand_fig.png
docs/control/figures/open-loop-n2.html
docs/control/figures/open-loop-n2.png
docs/control/figures/pyomo-n2.html
docs/control/figures/pyomo-n2.png
docs/developer_guide/adding_a_new_technology.md
docs/developer_guide/class_structure.md
docs/developer_guide/coding_guidelines.md
docs/developer_guide/describing_whats_in_classes.md
docs/developer_guide/features_not_currently_implemented.md
docs/developer_guide/why_make_h2integrate.md
docs/finance_models/ProFastBase.md
docs/finance_models/ProFastComp.md
docs/finance_models/ProFastNPV.md
docs/finance_models/finance_index.md
docs/finance_models/financial_analyses.md
docs/finance_models/numpy_financial_npv.md
docs/getting_started/environment_variables.md
docs/getting_started/expected_user_knowledge.md
docs/getting_started/install.md
docs/misc_resources/FAQ.md
docs/misc_resources/defining_filepaths.md
docs/misc_resources/glossary.md
docs/resource/goes_solar_v4_api.md
docs/resource/himawari_v3_api.md
docs/resource/meteosat_prime_meridian_v4_api.md
docs/resource/openmeteo_wind_archive.md
docs/resource/resource_index.md
docs/resource/solar_index.md
docs/resource/wind_index.md
docs/resource/wind_toolkit_v2_api.md
docs/technology_models/ammonia.md
docs/technology_models/atb_costs_pv.md
docs/technology_models/atb_costs_wind.md
docs/technology_models/co2.md
docs/technology_models/feedstocks.md
docs/technology_models/geologic_hydrogen.md
docs/technology_models/grid.md
docs/technology_models/hydrogen_storage.md
docs/technology_models/methanol.md
docs/technology_models/natural_gas.md
docs/technology_models/pvwattsv8_solar_pv.md
docs/technology_models/pysam_battery.md
docs/technology_models/run_of_river.md
docs/technology_models/simple_generic_storage.md
h2integrate-0.5.1.dist-info/licenses/LICENSE
h2integrate-0.5.1.dist-info/METADATA
h2integrate-0.5.1.dist-info/WHEEL
h2integrate-0.5.1.dist-info/top_level.txt
h2integrate-0.5.1.dist-info/RECORD
