Metadata-Version: 2.4
Name: h2integrate
Version: 0.5.1
Summary: Holistic Hybrids Optimization and Design Tool
Author: Kaitlin Brunik, Elenya Grant, Jared Thomas, Genevieve Starke, Jonathan Martin, Dakota Ramos, Mariya Koleva, Evan Reznicek, Rob Hammond, Brooke Stanislawski, Charlie Kiefer, Cameron Irmas, Sanjana Vijayshankar, Nicholas Riccobono, Cory Frontin, Caitlyn Clark, Aaron Barker, Abhineet Gupta, Benjamin Kee, Jennifer King
Maintainer-email: John Jasa <john.jasa@nrel.gov>, Christopher Bay <christopher.bay@nrel.gov>
License: BSD 3-Clause License
Project-URL: source, https://github.com/NREL/H2Integrate
Project-URL: documentation, https://h2integrate.readthedocs.io/
Project-URL: issues, https://github.com/NREL/H2Integrate/issues
Project-URL: changelog, https://github.com/NREL/H2Integrate/blob/main/CHANGELOG.md
Keywords: python3,hybrid-energy,wind-energy,solar-energy,layout-optimization
Classifier: Development Status :: 4 - Beta
Classifier: Intended Audience :: Developers
Classifier: Intended Audience :: Science/Research
Classifier: Intended Audience :: Other Audience
Classifier: License :: OSI Approved :: BSD License
Classifier: Natural Language :: English
Classifier: Operating System :: OS Independent
Classifier: Programming Language :: Python
Classifier: Programming Language :: Python :: 3 :: Only
Classifier: Programming Language :: Python :: 3.11
Classifier: Programming Language :: Python :: 3.12
Classifier: Topic :: Scientific/Engineering
Classifier: Topic :: Software Development :: Libraries :: Python Modules
Requires-Python: <3.14,>=3.11
License-File: LICENSE
Requires-Dist: attrs
Requires-Dist: CoolProp<7.0.0
Requires-Dist: floris==4.3
Requires-Dist: geopy
Requires-Dist: hopp>=3.3.0
Requires-Dist: jsonschema
Requires-Dist: matplotlib
Requires-Dist: multiprocessing-on-dill
Requires-Dist: numpy
Requires-Dist: numpy-financial
Requires-Dist: openmdao>=3.40.0
Requires-Dist: openpyxl
Requires-Dist: orbit-nrel
Requires-Dist: pandas>=2.0.3
Requires-Dist: ProFAST
Requires-Dist: Pyomo>=6.1.2
Requires-Dist: rainflow
Requires-Dist: ruamel.yaml
Requires-Dist: scipy
Requires-Dist: wombat>=0.11
Requires-Dist: geopy
Requires-Dist: openmeteo-requests
Requires-Dist: geopy
Requires-Dist: pyDOE3
Requires-Dist: rich>=13.7.0
Requires-Dist: requests-cache
Requires-Dist: retry_requests
Provides-Extra: develop
Requires-Dist: pre-commit; extra == "develop"
Requires-Dist: isort; extra == "develop"
Requires-Dist: ruff; extra == "develop"
Requires-Dist: pytest; extra == "develop"
Requires-Dist: pytest-subtests; extra == "develop"
Requires-Dist: responses; extra == "develop"
Requires-Dist: Plotly; extra == "develop"
Requires-Dist: jupyter-book<2; extra == "develop"
Requires-Dist: sphinxcontrib-napoleon; extra == "develop"
Provides-Extra: examples
Requires-Dist: jupyterlab; extra == "examples"
Provides-Extra: all
Requires-Dist: h2integrate[develop,examples]; extra == "all"
Dynamic: license-file
